[{"move":"4A","attribute":"B","guard":"All","startup":"6","active":"3","recovery":"11","frameAdv":"-2","blockstun":"11","hitstun":"12","untech":"12","hitstop":"9","invul":"-"},{"move":"5A","attribute":"B","guard":"All","startup":"7","active":"2(4)1","recovery":"19","frameAdv":"-3","blockstun":"16","hitstun":"17","untech":"17","hitstop":"11","invul":"-"},{"move":"5AA","attribute":"B","guard":"All","startup":"15","active":"6","recovery":"30","frameAdv":"-17","blockstun":"18","hitstun":"19","untech":"26","hitstop":"12","invul":"-"},{"move":"5AAA","attribute":"B","guard":"All","startup":"8","active":"2(3)2(3)2(3)2","recovery":"28","frameAdv":"-5","blockstun":"16","hitstun":"Stagger","untech":"17*3, 40","hitstop":"0/+8","invul":"-"},{"move":"5AAAA","attribute":"B","guard":"All","startup":"17","active":"10","recovery":"60","frameAdv":"-51","blockstun":"18","hitstun":"Launch","untech":"60","hitstop":"0","invul":"-"},{"move":"2A","attribute":"F","guard":"Low","startup":"9","active":"2","recovery":"15","frameAdv":"-3","blockstun":"13","hitstun":"14","untech":"14","hitstop":"10","invul":"-"},{"move":"5B","attribute":"B","guard":"All","startup":"10","active":"4","recovery":"19","frameAdv":"-6","blockstun":"16","hitstun":"17","untech":"17","hitstop":"11","invul":"-"},{"move":"5BB","attribute":"B","guard":"All","startup":"15","active":"8","recovery":"15","frameAdv":"-4","blockstun":"18","hitstun":"19","untech":"20","hitstop":"12","invul":"-"},{"move":"5BBB","attribute":"B","guard":"All","startup":"15","active":"3","recovery":"31","frameAdv":"-15","blockstun":"18","hitstun":"Launch","untech":"28","hitstop":"12","invul":"-"},{"move":"2B","attribute":"B","guard":"All","startup":"14","active":"3","recovery":"31","frameAdv":"-15","blockstun":"18","hitstun":"19","untech":"24","hitstop":"12","invul":"8-16 H"},{"move":"5C","attribute":"B","guard":"High","startup":"22","active":"3","recovery":"24","frameAdv":"-10","blockstun":"16","hitstun":"-","untech":"Down","hitstop":"12","invul":"-"},{"move":"2C","attribute":"F","guard":"Low","startup":"13","active":"4","recovery":"28","frameAdv":"-13","blockstun":"18","hitstun":"Launch","untech":"26","hitstop":"12","invul":"-"},{"move":"j.A","attribute":"H","guard":"High","startup":"9","active":"9","recovery":"28","frameAdv":"-","blockstun":"16","hitstun":"17","untech":"17","hitstop":"11","invul":"-"},{"move":"j.B(j.AA)","attribute":"H","guard":"High","startup":"10","active":"6","recovery":"20","frameAdv":"-","blockstun":"18","hitstun":"19","untech":"19","hitstop":"12","invul":"-"},{"move":"j.2B(j.BB)","attribute":"H","guard":"High","startup":"13","active":"5","recovery":"24","frameAdv":"-","blockstun":"18","hitstun":"19","untech":"19","hitstop":"12","invul":"-"},{"move":"j.C","attribute":"H","guard":"All","startup":"14","active":"3","recovery":"29+6L","frameAdv":"-","blockstun":"20","hitstun":"Launch","untech":"28","hitstop":"13","invul":"-"},{"move":"ForwardThrow","attribute":"T","guard":"Throw","startup":"7~30","active":"3","recovery":"23","frameAdv":"-","blockstun":"-","hitstun":"Stagger 28, Freeze","untech":"54","hitstop":"0*2, 12","invul":"-"},{"move":"4b+c","attribute":"T","guard":"Throw","startup":"7~30","active":"3","recovery":"23","frameAdv":"-","blockstun":"-","hitstun":"Freeze","untech":"54F","hitstop":"0, 12","invul":"-"},{"move":"a+d","attribute":"B","guard":"Air Unblockable","startup":"13","active":"3","recovery":"49","frameAdv":"-33","blockstun":"18","hitstun":"Launch","untech":"55","hitstop":"12","invul":"1~15 All"},{"move":"236a","attribute":"P","guard":"All","startup":"13","active":"-","recovery":"Total: 50","frameAdv":"-13","blockstun":"16","hitstun":"17","untech":"17","hitstop":"0/+8","invul":"-"},{"move":"j.236a","attribute":"P","guard":"All","startup":"20","active":"-","recovery":"Total: 44+11L","frameAdv":"-","blockstun":"16","hitstun":"17","untech":"17","hitstop":"0/+8","invul":"-"},{"move":"236b","attribute":"P","guard":"All","startup":"44","active":"-","recovery":"Total: 72","frameAdv":"+18","blockstun":"16","hitstun":"19","untech":"36","hitstop":"0/+8","invul":"-"},{"move":"j.236b","attribute":"P","guard":"All","startup":"24","active":"-","recovery":"Total: 72","frameAdv":"-","blockstun":"18","hitstun":"19","untech":"36","hitstop":"0/+8","invul":"-"},{"move":"214a","attribute":"F","guard":"Low","startup":"17","active":"8","recovery":"14+6L","frameAdv":"-4","blockstun":"16","hitstun":"Launch","untech":"26","hitstop":"11","invul":"-"},{"move":"Follow-upAttackMusouSenshouzan&gt;A/B/C","attribute":"H","guard":"All","startup":"14","active":"4","recovery":"6+20L","frameAdv":"-13","blockstun":"16","hitstun":"Down 24","untech":"30 + Down 24","hitstop":"8","invul":"-"},{"move":"214b","attribute":"F","guard":"Low","startup":"17","active":"10","recovery":"19+7L","frameAdv":"-10","blockstun":"16","hitstun":"Launch","untech":"26","hitstop":"11","invul":"-"},{"move":"Follow-upAttackMusouSenshouzan&gt;A/B/C","attribute":"B","guard":"All","startup":"14","active":"4","recovery":"6+20L","frameAdv":"-13","blockstun":"16","hitstun":"Down 24","untech":"30 + Down 24","hitstop":"8","invul":"-"},{"move":"j.214a","attribute":"H","guard":"All","startup":"13","active":"3","recovery":"37+8L","frameAdv":"-","blockstun":"16","hitstun":"Down 24","untech":"36 + Down 24","hitstop":"11","invul":"-"},{"move":"j.214b","attribute":"H","guard":"All, High","startup":"15","active":"1(9)3","recovery":"37+8L","frameAdv":"-","blockstun":"18","hitstun":"Down 24","untech":"80, 36 + Down 24","hitstop":"6, 12","invul":"-"},{"move":"236c","attribute":"P","guard":"All","startup":"27","active":"169","recovery":"Total: 52","frameAdv":"+36","blockstun":"16","hitstun":"Launch","untech":"36","hitstop":"0/+11","invul":"-"},{"move":"j.236c","attribute":"P","guard":"All","startup":"24","active":"169","recovery":"Total: 41+9L","frameAdv":"-","blockstun":"16","hitstun":"Launch","untech":"36","hitstop":"0/+11","invul":"-"},{"move":"214c","attribute":"F","guard":"Low","startup":"17","active":"12","recovery":"14+6L","frameAdv":"-2","blockstun":"18","hitstun":"Launch","untech":"25","hitstop":"12","invul":"-"},{"move":"Follow-upAttackMusouTousshugeki&gt;A/B/C","attribute":"B","guard":"All","startup":"14","active":"3","recovery":"5+11L","frameAdv":"-2","blockstun":"20","hitstun":"WBounce 50","untech":"WBounce 50","hitstop":"13","invul":"-"},{"move":"j.214c","attribute":"H","guard":"All, High","startup":"9","active":"1(7)3","recovery":"22+5L","frameAdv":"-","blockstun":"-","hitstun":"19, Down 28","untech":"80, 42 + Down 28","hitstop":"6, 12","invul":"-"},{"move":"5p","attribute":"B, H","guard":"All","startup":"(18)+16","active":"12[12(13)4]","recovery":"27 [4+20L]","frameAdv":"-22","blockstun":"16*2","hitstun":"Launch","untech":"26, 30 + Down 24","hitstop":"11, 8","invul":"-"},{"move":"6p","attribute":"P","guard":"All","startup":"(18)+44","active":"-","recovery":"Total: (18)+72","frameAdv":"+14","blockstun":"16","hitstun":"Launch","untech":"36","hitstop":"0/+8","invul":"-"},{"move":"4p","attribute":"B","guard":"All","startup":"(18)+10","active":"3","recovery":"38","frameAdv":"-22","blockstun":"18","hitstun":"Launch","untech":"60","hitstop":"16","invul":"-"},{"move":"236b+c","attribute":"P2","guard":"All","startup":"1+8","active":"-","recovery":"Total: 1+43","frameAdv":"-13~+3","blockstun":"18","hitstun":"Stagger 50","untech":"28 + Slide 39","hitstop":"0","invul":"1-8 All"},{"move":"214b+c","attribute":"P2","guard":"All","startup":"5+5","active":"-","recovery":"Total: 5+60","frameAdv":"-37","blockstun":"18","hitstun":"Launch","untech":"80","hitstop":"0/+30, 0*15[0/+30, 0*23]","invul":"1-11 All"},{"move":"214b+c","attribute":"P2","guard":"All","startup":"5+5","active":"-","recovery":"Total: 5+Until L+16[Total: 5+Until L+11]","frameAdv":"-","blockstun":"18","hitstun":"Launch","untech":"80","hitstop":"0/+30, 0*15[0/+30, 0*23]","invul":"1-13 All"},{"move":"YukikazeDistortionSkillDuo","attribute":"B","guard":"All","startup":"1+1","active":"15","recovery":"77","frameAdv":"-73","blockstun":"18","hitstun":"Freeze","untech":"Freeze","hitstop":"12","invul":"1-16 All"},{"move":"222b+c","attribute":"F","guard":"Low","startup":"6+14","active":"10","recovery":"95","frameAdv":"-86","blockstun":"18","hitstun":"-","untech":"-","hitstop":"0","invul":"1-19 All"}]